README.rst
gnusrss.py
setup.py
gnusrss.egg-info/PKG-INFO
gnusrss.egg-info/SOURCES.txt
gnusrss.egg-info/dependency_links.txt
gnusrss.egg-info/requires.txt
gnusrss.egg-info/top_level.txt