Metadata-Version: 1.1
Name: gnusrss
Version: 0.2.1.9
Summary: Post feeds to GNU Social.
Home-page: http://daemons.cf/cgit/gnusrss/about/
Author: drymer
Author-email: drymer@autistici.org
License: GPLv3
Download-URL: http://daemons.cf/cgit/gnusrss/snapshot/gnusrss-0.2.1.9.tar.gz
Platform: UNKNOWN
Classifier: Development Status :: 4 - Beta
Classifier: Programming Language :: Python
Classifier: Programming Language :: Python :: 3
Classifier: Programming Language :: Python :: 3.4
Classifier: Operating System :: OS Independent
Classifier: Operating System :: POSIX
Classifier: Intended Audience :: End Users/Desktop
